pygnssutils/__init__.py
pygnssutils/_version.py
pygnssutils/exceptions.py
pygnssutils/globals.py
pygnssutils/gnssmqttclient.py
pygnssutils/gnssmqttclient_cli.py
pygnssutils/gnssntripclient.py
pygnssutils/gnssntripclient_cli.py
pygnssutils/gnssreader.py
pygnssutils/gnssserver.py
pygnssutils/gnssserver_cli.py
pygnssutils/gnssstreamer.py
pygnssutils/gnssstreamer_cli.py
pygnssutils/helpers.py
pygnssutils/mqttmessage.py
pygnssutils/socket_server.py
pygnssutils-1.1.21.dist-info/licenses/LICENSE
pygnssutils-1.1.21.dist-info/METADATA
pygnssutils-1.1.21.dist-info/WHEEL
pygnssutils-1.1.21.dist-info/entry_points.txt
pygnssutils-1.1.21.dist-info/top_level.txt
pygnssutils-1.1.21.dist-info/RECORD
