Metadata-Version: 2.4
Name: pygnssutils
Version: 1.1.21
Summary: GNSS Command Line Utilities
Author-email: Steve Smith <semuadmin@semuconsulting.com>
Maintainer-email: Steve Smith <semuadmin@semuconsulting.com>
License-Expression: BSD-3-Clause
Project-URL: homepage, https://github.com/semuconsulting/pygnssutils
Project-URL: documentation, https://www.semuconsulting.com/pygnssutils/
Project-URL: repository, https://github.com/semuconsulting/pygnssutils
Project-URL: changelog, https://github.com/semuconsulting/pygnssutils/blob/master/RELEASE_NOTES.md
Classifier: Operating System :: OS Independent
Classifier: Development Status :: 5 - Production/Stable
Classifier: Environment :: MacOS X
Classifier: Environment :: Win32 (MS Windows)
Classifier: Environment :: X11 Applications
Classifier: Environment :: Console
Classifier: Intended Audience :: Developers
Classifier: Intended Audience :: Science/Research
Classifier: Intended Audience :: End Users/Desktop
Classifier: Programming Language :: Python :: 3
Classifier: Programming Language :: Python :: 3.10
Classifier: Programming Language :: Python :: 3.11
Classifier: Programming Language :: Python :: 3.12
Classifier: Programming Language :: Python :: 3.13
Classifier: Programming Language :: Python :: 3.14
Classifier: Topic :: Utilities
Classifier: Topic :: Software Development :: Libraries :: Python Modules
Classifier: Topic :: Scientific/Engineering :: GIS
Requires-Python: >=3.10
License-File: LICENSE
Requires-Dist: certifi>=2025.0.0
Requires-Dist: paho-mqtt>=2.1.0
Requires-Dist: pyserial>=3.5
Requires-Dist: pyspartn>=1.0.8
Requires-Dist: pyubx2>=1.2.59
Requires-Dist: pysbf2>=1.0.3
Requires-Dist: pyubxutils>=1.0.5
Requires-Dist: pyqgc>=0.1.2
Dynamic: license-file
